client/__init__.py
client/client.py
client/client_gui.py
client/const.py
client/jim.py
client_chat-0.0.1.dist-info/METADATA
client_chat-0.0.1.dist-info/WHEEL
client_chat-0.0.1.dist-info/top_level.txt
client_chat-0.0.1.dist-info/RECORD
