Metadata-Version: 2.1
Name: client-chat
Version: 0.0.1
Summary: Client 'Async chat' application
Home-page: UNKNOWN
Author: Sergey Karnaukhov
Author-email: s_karn_v@mail.ru
License: UNKNOWN
Platform: UNKNOWN
Requires-Dist: PyQt5
